pybenlogger/__init__.py
pybenlogger/config_logger.py
pybenlogger-2.0.0.dist-info/LICENSE
pybenlogger-2.0.0.dist-info/METADATA
pybenlogger-2.0.0.dist-info/WHEEL
pybenlogger-2.0.0.dist-info/top_level.txt
pybenlogger-2.0.0.dist-info/RECORD
